confz/__init__.py
confz/base_config.py
confz/change.py
confz/config_source.py
confz/exceptions.py
confz/loaders/__init__.py
confz/loaders/cl_arg_loader.py
confz/loaders/data_loader.py
confz/loaders/env_loader.py
confz/loaders/file_loader.py
confz/loaders/loader.py
confz/loaders/register.py
confz/py.typed
confz/validate.py
confz-2.1.0.dist-info/LICENSE
confz-2.1.0.dist-info/METADATA
confz-2.1.0.dist-info/WHEEL
confz-2.1.0.dist-info/RECORD
