Metadata-Version: 2.3
Name: confz
Version: 2.1.0
Summary: ConfZ is a configuration management library for Python based on pydantic.
License: MIT
Keywords: Configuration Management,Config Management
Author: Zühlke
Requires-Python: >=3.8.0,<4.0.0
Classifier: Intended Audience :: Developers
Classifier: License :: OSI Approved :: MIT License
Classifier: Operating System :: OS Independent
Classifier: Programming Language :: Python
Classifier: Programming Language :: Python :: 3
Classifier: Programming Language :: Python :: 3.8
Classifier: Programming Language :: Python :: 3.9
Classifier: Programming Language :: Python :: 3.10
Classifier: Programming Language :: Python :: 3.11
Classifier: Programming Language :: Python :: 3.12
Classifier: Programming Language :: Python :: 3.13
Classifier: Topic :: Software Development :: Libraries :: Python Modules
Requires-Dist: PyYAML (>=5.4.1,<7.0.0)
Requires-Dist: pydantic (>=1.9.0,<3.0.0)
Requires-Dist: python-dotenv (>=0.19.2,<2.0.0)
Requires-Dist: toml (>=0.10.2,<0.11.0)
Project-URL: Documentation, https://confz.readthedocs.io
Project-URL: Homepage, https://github.com/Zuehlke/ConfZ
Project-URL: Repository, https://github.com/Zuehlke/ConfZ
